Xioyu_kjnd/init.py
Xioyu_kjnd/multiply.py
xioyu_kjnd-0.1.0.dist-info/METADATA
xioyu_kjnd-0.1.0.dist-info/WHEEL
xioyu_kjnd-0.1.0.dist-info/top_level.txt
xioyu_kjnd-0.1.0.dist-info/RECORD
