Metadata-Version: 2.4
Name: Xioyu_kjnd
Version: 0.1.0
Summary: Demo package for PyPI publish
Author-email: Brunda Adiga <brunda.v@adaglobal.com>
License: MIT
Requires-Python: >=3.6
